snap/__init__.py
snap/_snap.pyd
snap/snap.py
snap/snapx/__init__.py
snap/snapx/convert.py
snap/snapx/exception.py
snap/snapx/relabel.py
snap/snapx/algorithms/__init__.py
snap/snapx/algorithms/dag.py
snap/snapx/algorithms/centrality/__init__.py
snap/snapx/algorithms/centrality/snap_cent.py
snap/snapx/algorithms/community/__init__.py
snap/snapx/algorithms/community/snap_cmty.py
snap/snapx/algorithms/components/__init__.py
snap/snapx/algorithms/components/components.py
snap/snapx/algorithms/shortest_paths/__init__.py
snap/snapx/algorithms/shortest_paths/unweighted.py
snap/snapx/algorithms/shortest_paths/weighted.py
snap/snapx/classes/__init__.py
snap/snapx/classes/_nodeiter.py
snap/snapx/classes/attrdict.py
snap/snapx/classes/coreviews.py
snap/snapx/classes/digraph.py
snap/snapx/classes/filters.py
snap/snapx/classes/function.py
snap/snapx/classes/graph.py
snap/snapx/classes/graphviews.py
snap/snapx/classes/reportviews.py
snap/snapx/classes/tests/__init__.py
snap/snapx/classes/tests/test_attrdict.py
snap/snapx/classes/tests/test_coreviews.py
snap/snapx/classes/tests/test_graph.py
snap/snapx/classes/tests/test_reportviews.py
snap/snapx/generators/__init__.py
snap/snapx/generators/classic.py
snap/snapx/generators/ego.py
snap/snapx/testing/__init__.py
snap/snapx/testing/utils.py
snap/snapx/utils/__init__.py
snap/snapx/utils/decorator.py
snap/snapx/utils/decorators.py
snap/snapx/utils/misc.py
snap_stanford-6.0.0.dist-info/METADATA
snap_stanford-6.0.0.dist-info/WHEEL
snap_stanford-6.0.0.dist-info/top_level.txt
snap_stanford-6.0.0.dist-info/RECORD
