Metadata-Version: 2.1
Name: snap-stanford
Version: 6.0.0
Summary: SNAP (Stanford Network Analysis Platform) Python
Home-page: http://snap.stanford.edu
Author: snap.stanford.edu
License: 3-clause BSD, http://snap.stanford.edu/snap/license.html
Platform: UNKNOWN
Classifier: Programming Language :: Python :: 2
Classifier: Programming Language :: Python :: 3
Classifier: License :: OSI Approved :: BSD License
Classifier: Operating System :: MacOS
Classifier: Operating System :: Microsoft :: Windows
Classifier: Operating System :: POSIX :: Linux
Classifier: Topic :: Scientific/Engineering
